factory_generator/__init__.py
factory_generator/admin.py
factory_generator/apps.py
factory_generator/fields_faker.py
factory_generator/generator.py
factory_generator/models.py
factory_generator/tests.py
factory_generator/utils.py
factory_generator/views.py
factory_generator/management/__init__.py
factory_generator/management/commands/__init__.py
factory_generator/management/commands/generate_factories.py
factory_generator/migrations/__init__.py
factory_generator/templates/factory_generator/app-init.py-tpl
factory_generator/templates/factory_generator/base-factory.py-tpl
factory_generator/templates/factory_generator/choiceslist.py-tpl
factory_generator/templates/factory_generator/default.py-tpl
factory_generator/templates/factory_generator/factory.py-tpl
factory_generator/templates/factory_generator/manytomany.py-tpl
django_factory_generator-1.0.4.dist-info/LICENSE
django_factory_generator-1.0.4.dist-info/METADATA
django_factory_generator-1.0.4.dist-info/WHEEL
django_factory_generator-1.0.4.dist-info/top_level.txt
django_factory_generator-1.0.4.dist-info/RECORD
